aiodanbooru/__init__.py
aiodanbooru/api.py
aiodanbooru/dispatcher.py
aiodanbooru/models.py
aiodanbooru/base/__init__.py
aiodanbooru/base/filters.py
aiodanbooru/base/handler.py
aiodanbooru-1.1.1.dist-info/LICENSE
aiodanbooru-1.1.1.dist-info/METADATA
aiodanbooru-1.1.1.dist-info/WHEEL
aiodanbooru-1.1.1.dist-info/top_level.txt
aiodanbooru-1.1.1.dist-info/RECORD
